{
    "package": "com.infologic.mathmagiclite",
    "verified": false,
    "authors": [
        "ZHider"
    ],
    "recommendation": "recommended",
    "behaviors": [
        "abuse"
    ],
    "observers": [
        {
            "source": "infologic.mathmagic",
            "target": "Pictures/MathMagic Lite",
            "description": "saved_pictures",
            "call_media_scan": true,
            "add_to_downloads": false,
            "allow_child": true,
            "allow_temp": false
        }
    ]
}