{
    "package": "com.netease.mobimail",
    "verified": false,
    "authors": [
        "UVJkiNTQ"
    ],
    "last_update": {
        "timestamp": 1573909761
    },
    "recommendation": "@recommended",
    "behaviors": [
        "@abuse"
    ],
    "export_folders": {
        "data": {
            "saved_pictures_0": {
                "title": "@saved_pictures",
                "source": "Netease/163mail/pictures",
                "target": "Pictures/NeteaseMail",
                "call_media_scan": true
            },
            "downloaded_files_0": {
                "title": "@downloaded_files",
                "source": "Netease/163mail/网易邮箱",
                "target": "Download/NeteaseMail",
                "call_media_scan": true,
                "add_to_downloads": true
            }
        }
    }
}