{
    "package": "dstudio.tool.instasave",
    "verified": false,
    "authors": [
        "sweet2honey"
    ],
    "last_update": {
        "timestamp": 1573909761
    },
    "recommendation": "@recommended",
    "behaviors": [
        "@abuse"
    ],
    "export_folders": {
        "data": {
            "saved_files_0": {
                "title": "@saved_files",
                "source": "QuickSave",
                "target": "Pictures/QuickSave",
                "call_media_scan": true,
                "add_to_downloads": true,
                "allow_child": false,
                "allow_temp": false
            },
            "saved_files_1": {
                "title": "@saved_files",
                "source": "QuickSave Videos",
                "target": "Pictures/QuickSave Videos",
                "call_media_scan": true,
                "add_to_downloads": true,
                "allow_child": false,
                "allow_temp": false
            }
        }
    }
}